siriusx/__init__.py
siriusx/core.py
siriusx-0.2.0.dist-info/METADATA
siriusx-0.2.0.dist-info/WHEEL
siriusx-0.2.0.dist-info/top_level.txt
siriusx-0.2.0.dist-info/RECORD
