Metadata-Version: 2.4
Name: siriusx
Version: 0.2.0
Summary: OpenDAQ-based Python wrapper for Dewesoft Sirius X measurement devices
Project-URL: Homepage, https://github.com/ladisk/siriusx
Project-URL: Repository, https://github.com/ladisk/siriusx
Classifier: Development Status :: 3 - Alpha
Classifier: Intended Audience :: Developers
Classifier: Intended Audience :: Science/Research
Classifier: Topic :: Scientific/Engineering
Classifier: Programming Language :: Python :: 3
Classifier: Programming Language :: Python :: 3.8
Classifier: Programming Language :: Python :: 3.9
Classifier: Programming Language :: Python :: 3.10
Classifier: Programming Language :: Python :: 3.11
Classifier: Programming Language :: Python :: 3.12
Requires-Python: >=3.8
Requires-Dist: opendaq
Requires-Dist: numpy
